{
  "total": [
    {
      "id": "61587849793131",
      "count": 2
    },
    {
      "id": "61581197276223",
      "count": 3
    },
    {
      "id": "61580581227896",
      "count": 2
    },
    {
      "id": "61583909139073",
      "count": 0
    }
  ],
  "month": [
    {
      "id": "61587849793131",
      "count": 2
    },
    {
      "id": "61581197276223",
      "count": 3
    },
    {
      "id": "61580581227896",
      "count": 2
    },
    {
      "id": "61583909139073",
      "count": 0
    }
  ],
  "week": [
    {
      "id": "61587849793131",
      "count": 2
    },
    {
      "id": "61581197276223",
      "count": 3
    },
    {
      "id": "61580581227896",
      "count": 2
    },
    {
      "id": "61583909139073",
      "count": 0
    }
  ],
  "day": [
    {
      "id": "61587849793131",
      "count": 2
    },
    {
      "id": "61581197276223",
      "count": 3
    },
    {
      "id": "61580581227896",
      "count": 2
    },
    {
      "id": "61583909139073",
      "count": 0
    }
  ],
  "lastDay": 15,
  "lastWeek": 12,
  "lastMonth": 2
}